operat/__init__.py
operat/operations.py
operat-0.1.0.dist-info/licenses/LICENSE
operat-0.1.0.dist-info/METADATA
operat-0.1.0.dist-info/WHEEL
operat-0.1.0.dist-info/top_level.txt
operat-0.1.0.dist-info/RECORD
